sapiensqa/__01010101.py
sapiensqa/__init__.py
sapiensqa/core.py
sapiensqa/requirements.txt
sapiensqa/sapiensqa.py
sapiensqa-1.0.2.dist-info/LICENSE.txt
sapiensqa-1.0.2.dist-info/METADATA
sapiensqa-1.0.2.dist-info/WHEEL
sapiensqa-1.0.2.dist-info/top_level.txt
sapiensqa-1.0.2.dist-info/RECORD
