Metadata-Version: 2.1
Name: sapiensqa
Version: 1.0.2
Summary: SapiensQA (Question and Answer) is a proprietary Machine Learning algorithm for creating Natural Language Processing models where the answers are previously known.
Home-page: https://github.com/sapiens-technology/SapiensQA
Author: SAPIENS TECHNOLOGY
License: Proprietary Software
Project-URL: Source code, https://github.com/sapiens-technology/SapiensQA
Project-URL: Download, https://github.com/sapiens-technology/SapiensQA/archive/refs/heads/main.zip
Keywords: Sapiens,Artificial Intelligence,Machine Learning,Natural Language Processing,AI,ML,NLP,ChatBot
License-File: LICENSE.txt
Requires-Dist: requests ==2.31.0
Requires-Dist: PyPDF2 ==3.0.1
Requires-Dist: pdfplumber ==0.10.2
Requires-Dist: docx2txt ==0.8
Requires-Dist: beautifulsoup4 ==4.12.2
